dev_env/__init__.py
dev_env/tests/__init__.py
dev_env-0.6.21.data/scripts/add-new-changelog-dot-md-release.py
dev_env-0.6.21.data/scripts/build-python-package.sh
dev_env-0.6.21.data/scripts/build-readme-dot-rst.sh
dev_env-0.6.21.data/scripts/changelog-dot-md-release-comments.py
dev_env-0.6.21.data/scripts/create-dummy-docker-container.sh
dev_env-0.6.21.data/scripts/create-github-release.sh
dev_env-0.6.21.data/scripts/cut-changelog-dot-md.py
dev_env-0.6.21.data/scripts/cut-release.sh
dev_env-0.6.21.data/scripts/docker-destructive-cleanup.sh
dev_env-0.6.21.data/scripts/get-circle-ci-executor.sh
dev_env-0.6.21.data/scripts/python-increment-version.sh
dev_env-0.6.21.data/scripts/python-version.sh
dev_env-0.6.21.data/scripts/repo-root-dir.sh
dev_env-0.6.21.data/scripts/repo.sh
dev_env-0.6.21.data/scripts/run-bandit.sh
dev_env-0.6.21.data/scripts/run-circleci.sh
dev_env-0.6.21.data/scripts/run-codecov-uploader.sh
dev_env-0.6.21.data/scripts/run-flake8.sh
dev_env-0.6.21.data/scripts/run-jsonlint.sh
dev_env-0.6.21.data/scripts/run-markdownlint.sh
dev_env-0.6.21.data/scripts/run-pip-check.sh
dev_env-0.6.21.data/scripts/run-repo-security-scanner.sh
dev_env-0.6.21.data/scripts/run-semantic-release.sh
dev_env-0.6.21.data/scripts/run-shelllint.sh
dev_env-0.6.21.data/scripts/run-unit-tests.sh
dev_env-0.6.21.data/scripts/run-yamllint.sh
dev_env-0.6.21.data/scripts/upload-dist-to-pypi.sh
dev_env-0.6.21.dist-info/LICENSE
dev_env-0.6.21.dist-info/METADATA
dev_env-0.6.21.dist-info/WHEEL
dev_env-0.6.21.dist-info/top_level.txt
dev_env-0.6.21.dist-info/RECORD
