Metadata-Version: 2.1
Name: dev-env
Version: 0.6.21
Summary: Dev Env
Home-page: https://github.com/simonsdave/dev-env
Author: Dave Simons
Author-email: simonsdave@gmail.com
Maintainer: Dave Simons
Maintainer-email: simonsdave@gmail.com
License: MIT
Download-URL: https://github.com/simonsdave/dev-env/tarball/v0.6.21
Keywords: development,tools
Platform: UNKNOWN
Classifier: Development Status :: 5 - Production/Stable
Classifier: Intended Audience :: Developers
Classifier: Natural Language :: English
Classifier: License :: OSI Approved :: MIT License
Classifier: Operating System :: OS Independent
Classifier: Programming Language :: Python
Classifier: Programming Language :: Python :: 3.9
Classifier: Programming Language :: Python :: Implementation :: CPython
Classifier: Topic :: Software Development :: Libraries :: Python Modules
